{
  "parent": "minecraft:recipes/root",
  "rewards": {
    "recipes": [
      "supersentaicraft:battle_fever/kenya_battleceiver",
      "supersentaicraft:battle_fever/kenya_whip"
    ]
  },
  "criteria": {
    "has_item": {
      "trigger": "minecraft:inventory_changed",
      "conditions": {
        "items": [
          {
            "item": "supersentaicraft:kenya_badge"
          }
        ]
      }
    },
    "has_the_recipe": {
      "trigger": "minecraft:recipe_unlocked",
      "conditions": {
        "recipe": "supersentaicraft:battle_fever/kenya_battleceiver"
      }
    },
    "has_the_recipe1": {
      "trigger": "minecraft:recipe_unlocked",
      "conditions": {
        "recipe": "supersentaicraft:battle_fever/kenya_whip"
      }
    }
  },
  "requirements": [
    [
      "has_item",
      "has_the_recipe",
      "has_the_recipe1"
    ]
  ]
}