{
  "parent": "minecraft:recipes/root",
  "rewards": {
    "recipes": [
      "supersentaicraft:goggle_v/black_goggle_brace",
      "supersentaicraft:goggle_v/black_hammer",
      "supersentaicraft:goggle_v/black_club",
      "supersentaicraft:goggle_v/black_emerald_nunchuck"
    ]
  },
  "criteria": {
    "has_item": {
      "trigger": "minecraft:inventory_changed",
      "conditions": {
        "items": [
          {
            "item": "supersentaicraft:angkor_wat_emerald"
          }
        ]
      }
    }
  },
  "requirements": [
    [
      "has_item"
    ]
  ]
}