{
  "parent": "minecraft:recipes/root",
  "rewards": {
    "recipes": [
      "supersentaicraft:gingaman/pink_ginga_brace",
      "supersentaicraft:gingaman/kiba_arrow",
      "supersentaicraft:gingaman/beast_attack_rod_pink"
    ]
  },
  "criteria": {
    "has_logo": {
      "trigger": "minecraft:inventory_changed",
      "conditions": {
        "items": [
          {
            "item": "supersentaicraft:pink_ginga_medal"
          }
        ]
      }
    }
  },
  "requirements": [
    [
      "has_logo"
    ]
  ]
}