{
  "parent": "minecraft:recipes/root",
  "rewards": {
    "recipes": [
      "supersentaicraft:pink_goggle_brace",
      "supersentaicraft:goggle_sabre4",
      "supersentaicraft:goggle_golden_spear4",
      "supersentaicraft:pink_hammer"
    ]
  },
  "criteria": {
    "has_item": {
      "trigger": "minecraft:inventory_changed",
      "conditions": {
        "items": [
          {
            "item": "supersentaicraft:mayan_diamond"
          }
        ]
      }
    },
    "has_the_recipe": {
      "trigger": "minecraft:recipe_unlocked",
      "conditions": {
        "recipe": "supersentaicraft:pink_goggle_brace"
      }
    },
    "has_the_recipe1": {
      "trigger": "minecraft:recipe_unlocked",
      "conditions": {
        "recipe": "supersentaicraft:goggle_sabre4"
      }
    },
    "has_the_recipe2": {
      "trigger": "minecraft:recipe_unlocked",
      "conditions": {
        "recipe": "supersentaicraft:goggle_golden_spear4"
      }
    },
    "has_the_recipe3": {
      "trigger": "minecraft:recipe_unlocked",
      "conditions": {
        "recipe": "supersentaicraft:pink_hammer"
      }
    }
  },
  "requirements": [
    [
      "has_item",
      "has_the_recipe",
      "has_the_recipe1",
      "has_the_recipe2",
      "has_the_recipe3"
    ]
  ]
}