{
  "parent": "minecraft:recipes/root",
  "rewards": {
    "recipes": [
      "supersentaicraft:abaranger/mecha/oo_abaren_oh_head"
    ]
  },
  "criteria": {
    "has_logo": {
      "trigger": "minecraft:inventory_changed",
      "conditions": {
        "items": [
          {
            "item": "supersentaicraft:max_ohja_head"
          }
        ]
      }
    },
    "has_the_recipe": {
      "trigger": "minecraft:recipe_unlocked",
      "conditions": {
        "recipe": "supersentaicraft:abaranger/mecha/oo_abaren_oh_head"
      }
    }
  },
  "requirements": [
    [
      "has_logo",
      "has_the_recipe"
    ]
  ]
}